jax-stubs/__init__.py
jax-stubs/__init__.pyi
jax-stubs/nn/__init__.pyi
jax-stubs/numpy/__init__.pyi
tensor_annotations_jax_stubs-2.0.3.dist-info/METADATA
tensor_annotations_jax_stubs-2.0.3.dist-info/WHEEL
tensor_annotations_jax_stubs-2.0.3.dist-info/top_level.txt
tensor_annotations_jax_stubs-2.0.3.dist-info/RECORD
